runtests.py
setup.py
django_pluggable.egg-info/PKG-INFO
django_pluggable.egg-info/SOURCES.txt
django_pluggable.egg-info/dependency_links.txt
django_pluggable.egg-info/requires.txt
django_pluggable.egg-info/top_level.txt