Metadata-Version: 1.1
Name: django-pluggable
Version: 0.0.1
Summary: Testrunner for pluggable apps.
Home-page: https://github.com/antonagestam/django-pluggable/
Author: Anton Agestam
Author-email: msn@antonagestam.se
License: The MIT License (MIT)
Platform: UNKNOWN
Classifier: Programming Language :: Python :: 2.7
Classifier: Programming Language :: Python :: 3
